py_requirements_guesser/__init__.py
py_requirements_guesser/cli.py
py_requirements_guesser/guesser.py
py_requirements_guesser/utils.py
py_requirements_guesser-0.1.0.dist-info/LICENSE
py_requirements_guesser-0.1.0.dist-info/METADATA
py_requirements_guesser-0.1.0.dist-info/WHEEL
py_requirements_guesser-0.1.0.dist-info/entry_points.txt
py_requirements_guesser-0.1.0.dist-info/top_level.txt
py_requirements_guesser-0.1.0.dist-info/RECORD
