Metadata-Version: 2.1
Name: py-requirements-guesser
Version: 0.1.0
Summary: Guess requirements.txt versions based on Git history
Home-page: https://github.com/j3rome/py-requirements-guesser
Author: Jerome Abdelnour
License: UNKNOWN
Platform: UNKNOWN
Classifier: Programming Language :: Python :: 3
Classifier: License :: OSI Approved :: GNU General Public License v3 (GPLv3)
Classifier: Operating System :: OS Independent
Requires-Python: >=3.6
License-File: LICENSE
